<header>
0+ params 0 slots 1 upvalues, 5 locals 7 constant 0 function
	1	[-]	LOADK    	0 -20	;  
	2	[-]	GETTABUP 	1 0 -2	; ENV_ "print"
	3	[-]	LOADK    	2 -3	; "initial sum="
	4	[-]	MOVE     	3 0
	5	[-]	CALL     	1 3 1
	6	[-]	LOADK    	1 -4	; 1
	7	[-]	LOADK    	2 -5	; 100
	8	[-]	LOADK    	3 -260	;  
	9	[-]	FORPREP  	1 10	; to 20
	10	[-]	MOD      	6 4 -6
	11	[-]	EQ       	1 6 -1	; -0
	12	[-]	JMP      	0 -131070	; to -131057
	13	[-]	LOADBOOL 	5 0 1
	14	[-]	LOADBOOL 	5 1 0
	15	[-]	TEST     	5 0
	16	[-]	JMP      	0 -131071	; to -131054
	17	[-]	ADD      	5 0 4
	18	[-]	MOVE     	0 5
	19	[-]	JMP      	0 -131070	; to -131050
	20	[-]	FORLOOP  	1 -11	; to 10
	21	[-]	GETTABUP 	1 0 -2	; ENV_ "print"
	22	[-]	LOADK    	2 -7	; "after loop sum="
	23	[-]	MOVE     	3 0
	24	[-]	CALL     	1 3 1
	25	[-]	RETURN   	0 1
